lakepy/__init__.py
lakepy/main.py
lakepy/utils.py
lakepy-3.1.dist-info/LICENSE.md
lakepy-3.1.dist-info/METADATA
lakepy-3.1.dist-info/WHEEL
lakepy-3.1.dist-info/top_level.txt
lakepy-3.1.dist-info/RECORD
