Metadata-Version: 2.1
Name: lakepy
Version: 3.1
Summary: Provides access to the Global Lake Level Database and extended functionality for lake water level analysis
Home-page: https://github.com/ESIPFed/LakePy
Author: James H. Gearon & John D. Franey
Author-email: jhgearon@iu.edu
License: MIT License
Platform: UNKNOWN
License-File: LICENSE.md
Requires-Dist: pymysql
Requires-Dist: pandas
Requires-Dist: numpy
Requires-Dist: matplotlib
Requires-Dist: seaborn
Requires-Dist: plotly
Requires-Dist: geopandas
Requires-Dist: shapely
Requires-Dist: contextily
Requires-Dist: more-itertools (==8.4)
Requires-Dist: tabulate
Requires-Dist: ipython
Requires-Dist: leafmap
Requires-Dist: scaleogram
Requires-Dist: statsmodels
